{
  "user_repo": "michaeldv/awesome_print",
  "dep_repo": "defunkt/fakefs",
  "dep_date": "2011-11-09 02:30:50 UTC",
  "dep_commit_id": "3d9bdc4e9b75daccfdfec29237fe2a26d87c3950",
  "social_date": "2011-05-05 22:39:09 UTC",
  "devs": [
    "michaeldv"
  ],
  "interactions": [
    {
      "dev_id": "michaeldv",
      "repo": "michaeldv/awesome_print",
      "type": "commit",
      "id": "0bd3425caf449e411cd5caecf60d4f80afbea851",
      "date": "2014-12-18T05:07:35Z"
    },
    {
      "dev_id": "michaeldv",
      "repo": "michaeldv/awesome_print",
      "type": "commit",
      "id": "cb525de776b73bd71f7b4fb84f5e2fa037e078a8",
      "date": "2014-12-18T05:03:19Z"
    },
    {
      "dev_id": "michaeldv",
      "repo": "michaeldv/awesome_print",
      "type": "commit",
      "id": "f36e788584801aa528a284693b54faeee4467a6d",
      "date": "2013-11-05T18:58:45Z"
    },
    {
      "dev_id": "michaeldv",
      "repo": "michaeldv/awesome_print",
      "type": "commit",
      "id": "33026612fcc0914a09ef64ff082da4fece95adf2",
      "date": "2013-10-08T22:36:26Z"
    },
    {
      "dev_id": "michaeldv",
      "repo": "michaeldv/awesome_print",
      "type": "commit",
      "id": "1e9f34b98fcdfe07973d1f1a57524ee72d992b01",
      "date": "2013-10-05T18:11:48Z"
    },
    {
      "dev_id": "michaeldv",
      "repo": "michaeldv/awesome_print",
      "type": "commit",
      "id": "dd0707f9890f50c3f66e8260f7eb0e048b044c6a",
      "date": "2013-09-25T22:27:15Z"
    },
    {
      "dev_id": "michaeldv",
      "repo": "michaeldv/awesome_print",
      "type": "commit",
      "id": "84573bcb859311808e53baadbdc292d49e2ac943",
      "date": "2013-09-24T19:26:46Z"
    },
    {
      "dev_id": "michaeldv",
      "repo": "michaeldv/awesome_print",
      "type": "commit",
      "id": "fb070acab0d19428244f9474243b5d6f996642b9",
      "date": "2013-09-24T19:18:44Z"
    },
    {
      "dev_id": "michaeldv",
      "repo": "michaeldv/awesome_print",
      "type": "commit",
      "id": "6a820e1f730cabe227233c9e4a0859129173a011",
      "date": "2013-09-21T07:29:18Z"
    },
    {
      "dev_id": "michaeldv",
      "repo": "michaeldv/awesome_print",
      "type": "commit",
      "id": "79a11bc33d33d7f0e2f836deaf4f451e8b459cd0",
      "date": "2013-09-21T06:59:59Z"
    },
    {
      "dev_id": "michaeldv",
      "repo": "michaeldv/awesome_print",
      "type": "commit",
      "id": "70dd2e39ae0b6b1882e907b8badab7e5f5cc2b28",
      "date": "2013-09-20T04:45:01Z"
    },
    {
      "dev_id": "michaeldv",
      "repo": "michaeldv/awesome_print",
      "type": "commit",
      "id": "4cd87b05fc93e8a5a40b66d7170a17760f7af4f3",
      "date": "2013-09-20T04:38:28Z"
    },
    {
      "dev_id": "michaeldv",
      "repo": "michaeldv/awesome_print",
      "type": "commit",
      "id": "3723f677cf69197af75b4a3752742cd43ea68081",
      "date": "2013-09-20T04:24:38Z"
    },
    {
      "dev_id": "michaeldv",
      "repo": "michaeldv/awesome_print",
      "type": "commit",
      "id": "acd42b0c5063f51337bff307d2f8ca68bdb61fe8",
      "date": "2013-09-20T04:21:58Z"
    },
    {
      "dev_id": "michaeldv",
      "repo": "michaeldv/awesome_print",
      "type": "commit",
      "id": "7ccf4907ae99b0cb13e616fc318391e9de7b6bc6",
      "date": "2013-09-20T00:00:28Z"
    },
    {
      "dev_id": "michaeldv",
      "repo": "michaeldv/awesome_print",
      "type": "commit",
      "id": "514faad651a2f277c05eafc0a9a732b038c4cf07",
      "date": "2013-09-18T20:18:50Z"
    },
    {
      "dev_id": "michaeldv",
      "repo": "michaeldv/awesome_print",
      "type": "commit",
      "id": "86ff96d03c74ad0bbf85fc81c361108e91e707ce",
      "date": "2013-09-18T20:04:45Z"
    },
    {
      "dev_id": "michaeldv",
      "repo": "michaeldv/awesome_print",
      "type": "commit",
      "id": "a23c9a860df6fbedef88a791b735363ea702d555",
      "date": "2013-09-18T20:00:39Z"
    },
    {
      "dev_id": "michaeldv",
      "repo": "michaeldv/awesome_print",
      "type": "commit",
      "id": "115ffc6a60f1f9bce48a4cdfb693fc5a95e21570",
      "date": "2013-09-18T19:58:58Z"
    },
    {
      "dev_id": "michaeldv",
      "repo": "michaeldv/awesome_print",
      "type": "commit",
      "id": "4a5d30fb2c5cc7da77b6d1d05a9d61be40600e14",
      "date": "2013-09-18T19:56:47Z"
    },
    {
      "dev_id": "michaeldv",
      "repo": "michaeldv/awesome_print",
      "type": "commit",
      "id": "7a21c4b2634fd1ae11c3d36e82c20d505d1b9c0c",
      "date": "2013-09-18T19:52:25Z"
    },
    {
      "dev_id": "michaeldv",
      "repo": "michaeldv/awesome_print",
      "type": "commit",
      "id": "9fc48b11239b530ecdfc1a2b2cf0778ad729cc56",
      "date": "2013-09-18T19:49:46Z"
    },
    {
      "dev_id": "michaeldv",
      "repo": "michaeldv/awesome_print",
      "type": "commit",
      "id": "73e3590b3858657c484589613d5ca0354dca54dd",
      "date": "2013-09-18T19:43:41Z"
    },
    {
      "dev_id": "michaeldv",
      "repo": "michaeldv/awesome_print",
      "type": "commit",
      "id": "009113acc5a9c3b9d52aa6b5923297d507fa0559",
      "date": "2013-09-18T19:41:46Z"
    },
    {
      "dev_id": "michaeldv",
      "repo": "michaeldv/awesome_print",
      "type": "commit",
      "id": "225fe66ca0d99695f77ca59489a9a8f60438192a",
      "date": "2013-09-18T19:37:26Z"
    },
    {
      "dev_id": "michaeldv",
      "repo": "michaeldv/awesome_print",
      "type": "commit",
      "id": "4bb89e84ca13661fee2addb89d88476b7357a5ea",
      "date": "2013-09-18T19:32:48Z"
    },
    {
      "dev_id": "michaeldv",
      "repo": "michaeldv/awesome_print",
      "type": "commit",
      "id": "28c9577cb46b0183c7ea8b7c3a586328208c70b5",
      "date": "2013-06-18T04:00:43Z"
    },
    {
      "dev_id": "michaeldv",
      "repo": "michaeldv/awesome_print",
      "type": "commit",
      "id": "6e46a121842304a7de905d7405592a62be601abb",
      "date": "2012-11-24T04:31:04Z"
    },
    {
      "dev_id": "michaeldv",
      "repo": "michaeldv/awesome_print",
      "type": "commit",
      "id": "ee16be40bc7f05e7dca3e230476e0196592b8aa1",
      "date": "2012-09-11T23:18:01Z"
    },
    {
      "dev_id": "michaeldv",
      "repo": "michaeldv/awesome_print",
      "type": "commit",
      "id": "060ccb3914ac728f2d525731558976bffdd61d5c",
      "date": "2012-09-11T23:11:27Z"
    },
    {
      "dev_id": "michaeldv",
      "repo": "michaeldv/awesome_print",
      "type": "commit",
      "id": "e7c9378ea98a8e826b0fc6663f1fd604b51e946f",
      "date": "2012-09-11T23:01:56Z"
    },
    {
      "dev_id": "michaeldv",
      "repo": "michaeldv/awesome_print",
      "type": "commit",
      "id": "4462fce5fd1e2eea89e16081317ecb92c3e90798",
      "date": "2012-09-11T22:43:41Z"
    },
    {
      "dev_id": "michaeldv",
      "repo": "michaeldv/awesome_print",
      "type": "commit",
      "id": "0872a955b73a26f35abccaeab79cbb610a99da53",
      "date": "2012-09-11T22:41:33Z"
    },
    {
      "dev_id": "michaeldv",
      "repo": "michaeldv/awesome_print",
      "type": "commit",
      "id": "10efa1d60a463b05f14a4d2d1e73d2621cfa567c",
      "date": "2012-09-07T01:37:51Z"
    },
    {
      "dev_id": "michaeldv",
      "repo": "michaeldv/awesome_print",
      "type": "commit",
      "id": "5463de12e9a9682542e519fdc9122733491c1666",
      "date": "2012-09-07T01:11:13Z"
    },
    {
      "dev_id": "michaeldv",
      "repo": "michaeldv/awesome_print",
      "type": "commit",
      "id": "da0defa87a54edd1dd513113f850b1adf5419ac1",
      "date": "2012-09-06T23:34:11Z"
    },
    {
      "dev_id": "michaeldv",
      "repo": "michaeldv/awesome_print",
      "type": "commit",
      "id": "9b655ad63ace82bfd16a93ff492d1c6e96643be8",
      "date": "2012-09-06T05:25:52Z"
    },
    {
      "dev_id": "michaeldv",
      "repo": "michaeldv/awesome_print",
      "type": "commit",
      "id": "edee37c5c79bbeeb75bbad92bb93c4590ad891cf",
      "date": "2012-09-06T04:55:04Z"
    },
    {
      "dev_id": "michaeldv",
      "repo": "michaeldv/awesome_print",
      "type": "commit",
      "id": "67cde1be8d488a042ff2d79a5cd1143862155a17",
      "date": "2012-09-06T02:41:54Z"
    },
    {
      "dev_id": "michaeldv",
      "repo": "michaeldv/awesome_print",
      "type": "commit",
      "id": "5f00926d80677d999ae3c6a313399be613c734f0",
      "date": "2012-09-06T01:40:30Z"
    },
    {
      "dev_id": "michaeldv",
      "repo": "michaeldv/awesome_print",
      "type": "commit",
      "id": "ac3f7cb60b22de10a5348635cfed462aae16c41f",
      "date": "2012-09-06T00:52:22Z"
    },
    {
      "dev_id": "michaeldv",
      "repo": "michaeldv/awesome_print",
      "type": "commit",
      "id": "bef11700b5b03a2982c7f55ee60bfeb0435fd589",
      "date": "2012-09-04T04:22:05Z"
    },
    {
      "dev_id": "michaeldv",
      "repo": "michaeldv/awesome_print",
      "type": "commit",
      "id": "c7bdcd85e6c07b0102173975d76a536c8ab96d4a",
      "date": "2012-09-04T04:02:12Z"
    },
    {
      "dev_id": "michaeldv",
      "repo": "michaeldv/awesome_print",
      "type": "commit",
      "id": "39bf45e4d524e6e5beaad446ef21e3591c57dcb5",
      "date": "2012-09-04T00:26:27Z"
    },
    {
      "dev_id": "michaeldv",
      "repo": "michaeldv/awesome_print",
      "type": "commit",
      "id": "5f6d2268b06809fa960ff32aa550eea6b7231732",
      "date": "2012-09-03T21:59:36Z"
    },
    {
      "dev_id": "michaeldv",
      "repo": "michaeldv/awesome_print",
      "type": "commit",
      "id": "a939430d166f900a54d5ff6032d92767deb19900",
      "date": "2012-09-03T21:05:14Z"
    },
    {
      "dev_id": "michaeldv",
      "repo": "michaeldv/awesome_print",
      "type": "commit",
      "id": "fa958455ca3083cc58111e90d51114748882fce9",
      "date": "2012-09-03T20:57:10Z"
    },
    {
      "dev_id": "michaeldv",
      "repo": "michaeldv/awesome_print",
      "type": "commit",
      "id": "8a222fb70993fbfd3d40cbcb7b9ab3d810051319",
      "date": "2012-09-03T20:06:16Z"
    },
    {
      "dev_id": "michaeldv",
      "repo": "michaeldv/awesome_print",
      "type": "commit",
      "id": "eb295c106da8ff122e6efe71c21accb8eb692c37",
      "date": "2012-09-03T19:23:31Z"
    },
    {
      "dev_id": "michaeldv",
      "repo": "michaeldv/awesome_print",
      "type": "commit",
      "id": "fcdc3b6320678cf16dec576756b96e87d1e8c3a0",
      "date": "2012-09-03T18:57:16Z"
    },
    {
      "dev_id": "michaeldv",
      "repo": "michaeldv/awesome_print",
      "type": "commit",
      "id": "246f5f93ab89fe6ceda179f5f93dbc287937e83b",
      "date": "2012-09-03T18:54:32Z"
    },
    {
      "dev_id": "michaeldv",
      "repo": "michaeldv/awesome_print",
      "type": "commit",
      "id": "fea9567eb4562cbacbc135191e96ca58ded60558",
      "date": "2011-12-21T04:31:12Z"
    },
    {
      "dev_id": "michaeldv",
      "repo": "michaeldv/awesome_print",
      "type": "commit",
      "id": "9046eccf4ff1feb3818964cccc73845e877f079f",
      "date": "2011-12-21T04:04:07Z"
    },
    {
      "dev_id": "michaeldv",
      "repo": "michaeldv/awesome_print",
      "type": "commit",
      "id": "a2b93697673d0825e31ec7ec546e2e0f4a19c8a5",
      "date": "2011-12-20T07:10:38Z"
    },
    {
      "dev_id": "michaeldv",
      "repo": "michaeldv/awesome_print",
      "type": "commit",
      "id": "72b7cafb10aced59c166381aebf08f1f25091cea",
      "date": "2011-12-20T06:47:45Z"
    },
    {
      "dev_id": "michaeldv",
      "repo": "michaeldv/awesome_print",
      "type": "commit",
      "id": "c29f36e483358b0635a92877eb31b70d95db8bb7",
      "date": "2011-12-20T06:30:06Z"
    },
    {
      "dev_id": "michaeldv",
      "repo": "michaeldv/awesome_print",
      "type": "commit",
      "id": "3258a9bc631c95779ca45c43a2cf2b23812bc036",
      "date": "2011-12-18T23:49:43Z"
    },
    {
      "dev_id": "michaeldv",
      "repo": "michaeldv/awesome_print",
      "type": "commit",
      "id": "af1ba40b83296ca323dfbe19ed7e7e116077c95f",
      "date": "2011-12-17T00:01:28Z"
    },
    {
      "dev_id": "michaeldv",
      "repo": "michaeldv/awesome_print",
      "type": "commit",
      "id": "23687d770de38a4baf145dae346ebf707558e6e2",
      "date": "2011-12-16T21:24:14Z"
    },
    {
      "dev_id": "michaeldv",
      "repo": "michaeldv/awesome_print",
      "type": "commit",
      "id": "19c8e74e853f29f533ba88afa9065dab3d2f0cff",
      "date": "2011-12-14T00:02:55Z"
    },
    {
      "dev_id": "michaeldv",
      "repo": "michaeldv/awesome_print",
      "type": "commit",
      "id": "a48e74cb2f8ea7b5251f34de126a01b76fff63c2",
      "date": "2011-12-14T00:01:14Z"
    },
    {
      "dev_id": "michaeldv",
      "repo": "michaeldv/awesome_print",
      "type": "commit",
      "id": "71044fdd20d10430a5c18299e917427e7c20513d",
      "date": "2011-12-05T21:56:46Z"
    },
    {
      "dev_id": "michaeldv",
      "repo": "michaeldv/awesome_print",
      "type": "commit",
      "id": "db70523e43d323e9e48c1662ab1ae02ee6b3401c",
      "date": "2011-12-05T21:49:13Z"
    },
    {
      "dev_id": "michaeldv",
      "repo": "michaeldv/awesome_print",
      "type": "commit",
      "id": "2ad522d36e81545745770502d03235a5e6f006b2",
      "date": "2011-12-05T21:33:05Z"
    },
    {
      "dev_id": "michaeldv",
      "repo": "michaeldv/awesome_print",
      "type": "commit",
      "id": "2514c74440215ce92fbcb5dc48ea1e3964d865b0",
      "date": "2011-11-30T05:16:05Z"
    },
    {
      "dev_id": "michaeldv",
      "repo": "michaeldv/awesome_print",
      "type": "commit",
      "id": "58503538121c3dfeacefb8ae13a47682c0be98ed",
      "date": "2011-11-30T04:39:55Z"
    },
    {
      "dev_id": "michaeldv",
      "repo": "michaeldv/awesome_print",
      "type": "commit",
      "id": "32e76633e879d0783f0673cd20b30ad1623cfc4b",
      "date": "2011-11-30T04:26:00Z"
    },
    {
      "dev_id": "michaeldv",
      "repo": "michaeldv/awesome_print",
      "type": "commit",
      "id": "c96c2c654126d0f47fe2a6187db17be2adfc4f1e",
      "date": "2011-11-30T04:01:58Z"
    },
    {
      "dev_id": "michaeldv",
      "repo": "michaeldv/awesome_print",
      "type": "commit",
      "id": "91ac8e080dd4437f3d6cd5b819f4cc70ba007402",
      "date": "2011-11-30T03:58:55Z"
    },
    {
      "dev_id": "michaeldv",
      "repo": "michaeldv/awesome_print",
      "type": "commit",
      "id": "89b8fc92ef60c644aabbada5fae80a44ef8f33ce",
      "date": "2011-11-30T03:52:30Z"
    },
    {
      "dev_id": "michaeldv",
      "repo": "michaeldv/awesome_print",
      "type": "commit",
      "id": "f24462a53387b6ea8371cadc9dbaf7a975db62c0",
      "date": "2011-11-24T08:25:52Z"
    },
    {
      "dev_id": "michaeldv",
      "repo": "michaeldv/awesome_print",
      "type": "commit",
      "id": "c6d27131df6cb18f0156becc442fcfa8dc3a7c0b",
      "date": "2011-11-24T08:16:43Z"
    },
    {
      "dev_id": "michaeldv",
      "repo": "michaeldv/awesome_print",
      "type": "commit",
      "id": "fc23c998bb71f70d6d955f38c3ea3aa4a7a9022b",
      "date": "2011-11-24T06:48:51Z"
    },
    {
      "dev_id": "michaeldv",
      "repo": "michaeldv/awesome_print",
      "type": "commit",
      "id": "b6a02f200bedac191ccc6e4de7e858ab9dbb7ad5",
      "date": "2011-11-24T06:37:25Z"
    },
    {
      "dev_id": "michaeldv",
      "repo": "michaeldv/awesome_print",
      "type": "commit",
      "id": "84dc4295e51cf5983f84ec03d4b6f3b2a0071482",
      "date": "2011-11-24T05:47:05Z"
    },
    {
      "dev_id": "michaeldv",
      "repo": "michaeldv/awesome_print",
      "type": "commit",
      "id": "562201f7ddf1df8f98f961df9037d5b8147f186b",
      "date": "2011-11-24T05:33:03Z"
    },
    {
      "dev_id": "michaeldv",
      "repo": "michaeldv/awesome_print",
      "type": "commit",
      "id": "59b7099293feb608fb3a3ae60ab5512239f22466",
      "date": "2011-11-24T05:27:47Z"
    },
    {
      "dev_id": "michaeldv",
      "repo": "michaeldv/awesome_print",
      "type": "commit",
      "id": "3849b4a7bd7073998eced90da82469c26c03c7cb",
      "date": "2011-11-24T05:10:56Z"
    },
    {
      "dev_id": "michaeldv",
      "repo": "michaeldv/awesome_print",
      "type": "commit",
      "id": "2566e5c1b12a08721381201eaa19c94fa3521721",
      "date": "2011-11-09T06:07:27Z"
    },
    {
      "dev_id": "michaeldv",
      "repo": "michaeldv/awesome_print",
      "type": "commit",
      "id": "c88594a811a0c783a65beefd0f21167e6dd43e7b",
      "date": "2011-11-09T06:03:16Z"
    },
    {
      "dev_id": "michaeldv",
      "repo": "michaeldv/awesome_print",
      "type": "commit",
      "id": "02ea0da95cbc3833b222d11bf4f8fd03e5c913fe",
      "date": "2011-11-09T05:48:03Z"
    },
    {
      "dev_id": "michaeldv",
      "repo": "michaeldv/awesome_print",
      "type": "commit",
      "id": "d2c0a398e273286ed3f604e7d558eec4a9a44674",
      "date": "2011-11-09T05:27:02Z"
    },
    {
      "dev_id": "michaeldv",
      "repo": "michaeldv/awesome_print",
      "type": "commit",
      "id": "782e38268b9d8951a04a98bbe814e81a1935406d",
      "date": "2011-11-09T01:05:24Z"
    },
    {
      "dev_id": "michaeldv",
      "repo": "michaeldv/awesome_print",
      "type": "commit",
      "id": "ac5c9fa0435bab98d3be01a8fba8f1e195f9f376",
      "date": "2011-11-09T00:49:06Z"
    },
    {
      "dev_id": "michaeldv",
      "repo": "michaeldv/awesome_print",
      "type": "commit",
      "id": "8044c29b50fc9ec4d7264880d12dc4aa744c62cc",
      "date": "2011-11-08T22:50:16Z"
    },
    {
      "dev_id": "michaeldv",
      "repo": "michaeldv/awesome_print",
      "type": "commit",
      "id": "785109a66e9c8e60af66f7d01869713101a50758",
      "date": "2011-11-08T21:36:22Z"
    },
    {
      "dev_id": "michaeldv",
      "repo": "michaeldv/awesome_print",
      "type": "commit",
      "id": "3ee9e2d700c249e2d369416b1d6535a3da3a0d7e",
      "date": "2011-11-08T21:19:47Z"
    },
    {
      "dev_id": "michaeldv",
      "repo": "michaeldv/awesome_print",
      "type": "commit",
      "id": "3d9bdc4e9b75daccfdfec29237fe2a26d87c3950",
      "date": "2011-11-08T20:56:04Z"
    },
    {
      "dev_id": "michaeldv",
      "repo": "michaeldv/awesome_print",
      "type": "commit",
      "id": "50152e17e9fab7fcf039c24dfafa8d571a5d73aa",
      "date": "2011-11-08T19:05:16Z"
    },
    {
      "dev_id": "michaeldv",
      "repo": "michaeldv/awesome_print",
      "type": "commit",
      "id": "2e75a163874adcebc67329fb41849a302b182939",
      "date": "2011-06-02T05:51:45Z"
    },
    {
      "dev_id": "michaeldv",
      "repo": "michaeldv/awesome_print",
      "type": "commit",
      "id": "cb4a9ac2b55b8102b48b5a91a032b242fb56aad1",
      "date": "2011-06-02T05:47:20Z"
    },
    {
      "dev_id": "michaeldv",
      "repo": "michaeldv/awesome_print",
      "type": "commit",
      "id": "b8822574ecb55afc8f07599cb25e54a397e782c6",
      "date": "2011-05-14T04:07:34Z"
    },
    {
      "dev_id": "michaeldv",
      "repo": "michaeldv/awesome_print",
      "type": "commit",
      "id": "5de4abf3592286ad498e000dc59d3070e69856f0",
      "date": "2011-05-14T03:05:37Z"
    },
    {
      "dev_id": "michaeldv",
      "repo": "michaeldv/awesome_print",
      "type": "commit",
      "id": "5d76ded7ed10da9d8d89aa709b0634813ed91a58",
      "date": "2011-05-14T00:36:12Z"
    },
    {
      "dev_id": "michaeldv",
      "repo": "michaeldv/awesome_print",
      "type": "commit",
      "id": "17f6113aacbf4ca54054dc00c9a44d4eeb4521df",
      "date": "2011-05-14T00:06:04Z"
    },
    {
      "dev_id": "michaeldv",
      "repo": "michaeldv/awesome_print",
      "type": "commit",
      "id": "08730b1023125c649f86065f0fac8e471e9bce06",
      "date": "2011-05-13T23:48:47Z"
    },
    {
      "dev_id": "michaeldv",
      "repo": "michaeldv/awesome_print",
      "type": "commit",
      "id": "b538cca4c56796764088e81f41b3caa456550e42",
      "date": "2011-05-13T23:37:24Z"
    },
    {
      "dev_id": "michaeldv",
      "repo": "michaeldv/awesome_print",
      "type": "commit",
      "id": "7a35496b7fb16431b04b47f3033a58538e774d92",
      "date": "2011-05-13T23:24:01Z"
    },
    {
      "dev_id": "michaeldv",
      "repo": "michaeldv/awesome_print",
      "type": "commit",
      "id": "91b73c47fd3ee99e4dbb68a135789656e165d660",
      "date": "2011-05-13T22:23:28Z"
    },
    {
      "dev_id": "michaeldv",
      "repo": "michaeldv/awesome_print",
      "type": "commit",
      "id": "7202362241e2a473127de9fc74bdcdb5325c98a9",
      "date": "2011-05-13T22:14:34Z"
    },
    {
      "dev_id": "michaeldv",
      "repo": "michaeldv/awesome_print",
      "type": "commit",
      "id": "757227bd9faa36660df3d0978dd05cad9da3bf36",
      "date": "2011-05-13T22:10:06Z"
    },
    {
      "dev_id": "michaeldv",
      "repo": "michaeldv/awesome_print",
      "type": "commit",
      "id": "24b6192f57d2e3b7483057c8c4e7024d0ff6d3cc",
      "date": "2011-05-13T21:42:04Z"
    },
    {
      "dev_id": "michaeldv",
      "repo": "michaeldv/awesome_print",
      "type": "commit",
      "id": "894e35ebd90f79264dedb035d98c6a3f88bb51b0",
      "date": "2011-05-13T20:58:00Z"
    },
    {
      "dev_id": "michaeldv",
      "repo": "michaeldv/awesome_print",
      "type": "commit",
      "id": "b9cf4a4e0aa01b3920366b8b429a6644ca14c46d",
      "date": "2011-05-13T20:33:16Z"
    },
    {
      "dev_id": "michaeldv",
      "repo": "michaeldv/awesome_print",
      "type": "commit",
      "id": "62c07edea231d5e9737604072737bb9f7f0d6fdd",
      "date": "2011-05-13T20:22:01Z"
    },
    {
      "dev_id": "michaeldv",
      "repo": "michaeldv/awesome_print",
      "type": "commit",
      "id": "a861908fb7616a739237b3e9b5a66a460bc12a67",
      "date": "2011-05-07T18:50:04Z"
    },
    {
      "dev_id": "michaeldv",
      "repo": "michaeldv/awesome_print",
      "type": "commit",
      "id": "a9ec52c4b434b071c9f01c0f6a8c3456ab232106",
      "date": "2011-05-07T07:15:39Z"
    },
    {
      "dev_id": "michaeldv",
      "repo": "michaeldv/awesome_print",
      "type": "commit",
      "id": "4312fd7f5543a071304877d190f0f7d8fcb9d98c",
      "date": "2011-05-07T06:38:29Z"
    },
    {
      "dev_id": "michaeldv",
      "repo": "michaeldv/awesome_print",
      "type": "commit",
      "id": "f567dda7bd3b203a6d964e47ccf2553843a6d711",
      "date": "2011-05-07T00:35:49Z"
    },
    {
      "dev_id": "michaeldv",
      "repo": "michaeldv/awesome_print",
      "type": "commit",
      "id": "2fc756b5358cca969f8d9cd836c9c4e105d08551",
      "date": "2011-05-07T00:23:26Z"
    },
    {
      "dev_id": "michaeldv",
      "repo": "michaeldv/awesome_print",
      "type": "commit",
      "id": "cef1856d132bcee42369b7662146253939e0f173",
      "date": "2011-05-06T23:59:31Z"
    },
    {
      "dev_id": "michaeldv",
      "repo": "michaeldv/awesome_print",
      "type": "commit",
      "id": "9c30b5286c3e47a85f313654a285be8fbce9fd13",
      "date": "2011-05-06T22:20:52Z"
    },
    {
      "dev_id": "michaeldv",
      "repo": "michaeldv/awesome_print",
      "type": "commit",
      "id": "437810bff542a8e103637e9cdeb1a02f39e436a5",
      "date": "2011-05-06T21:49:51Z"
    },
    {
      "dev_id": "michaeldv",
      "repo": "michaeldv/awesome_print",
      "type": "commit",
      "id": "8a0f6fa97e2b0f18c22030e76249b93fa32521b6",
      "date": "2011-05-06T21:29:53Z"
    },
    {
      "dev_id": "michaeldv",
      "repo": "michaeldv/awesome_print",
      "type": "commit",
      "id": "e048d0fab5a22b8c9df3bcf03a027a934a9f415c",
      "date": "2011-05-06T21:08:00Z"
    },
    {
      "dev_id": "michaeldv",
      "repo": "michaeldv/awesome_print",
      "type": "commit",
      "id": "2af734076a67063aff1f9d3fffd4a4af578e1ea7",
      "date": "2011-05-06T21:07:35Z"
    },
    {
      "dev_id": "michaeldv",
      "repo": "michaeldv/awesome_print",
      "type": "commit",
      "id": "3efefd1f290cea943b263c92fe4c92bc1eb3f1b4",
      "date": "2011-05-06T17:10:46Z"
    },
    {
      "dev_id": "michaeldv",
      "repo": "michaeldv/awesome_print",
      "type": "commit",
      "id": "52bb3e7adba587fea7982fa74376ca3f590e5e51",
      "date": "2011-05-05T00:56:29Z"
    },
    {
      "dev_id": "michaeldv",
      "repo": "michaeldv/awesome_print",
      "type": "commit",
      "id": "b0e47f11d23ba19ac67b2b628da506b1268dd8f4",
      "date": "2011-05-05T00:55:31Z"
    },
    {
      "dev_id": "michaeldv",
      "repo": "michaeldv/awesome_print",
      "type": "commit",
      "id": "272380fe213cf0050798ad2331a81ab79306683d",
      "date": "2011-05-05T00:48:21Z"
    },
    {
      "dev_id": "michaeldv",
      "repo": "michaeldv/awesome_print",
      "type": "commit",
      "id": "4f163f2468d37440b9de50bdda57926c1d2dd8ea",
      "date": "2011-02-24T06:06:25Z"
    },
    {
      "dev_id": "michaeldv",
      "repo": "michaeldv/awesome_print",
      "type": "commit",
      "id": "62041f2aa49cd47de7cfe70317ffc5fc0cb301c3",
      "date": "2011-02-10T03:20:56Z"
    },
    {
      "dev_id": "michaeldv",
      "repo": "michaeldv/awesome_print",
      "type": "commit",
      "id": "dfbebd488769738ac854adf37c930ad1d31bb94f",
      "date": "2011-02-05T19:31:51Z"
    },
    {
      "dev_id": "michaeldv",
      "repo": "michaeldv/awesome_print",
      "type": "commit",
      "id": "0f14846fcd7356cabde6bfb40be6c5529eccfbdf",
      "date": "2011-02-03T06:59:31Z"
    },
    {
      "dev_id": "michaeldv",
      "repo": "michaeldv/awesome_print",
      "type": "commit",
      "id": "d71b885e6d255ee04ea819cb815a2a7a88e89f0c",
      "date": "2011-02-03T06:48:27Z"
    },
    {
      "dev_id": "michaeldv",
      "repo": "michaeldv/awesome_print",
      "type": "commit",
      "id": "27d5aa2c0ffd27c3eed35d5ed838ea3d6e345885",
      "date": "2011-02-03T06:43:55Z"
    },
    {
      "dev_id": "michaeldv",
      "repo": "michaeldv/awesome_print",
      "type": "commit",
      "id": "05265cb4e53b48199241fe8a26bd97a47e3541ea",
      "date": "2011-02-03T06:35:17Z"
    },
    {
      "dev_id": "michaeldv",
      "repo": "michaeldv/awesome_print",
      "type": "commit",
      "id": "f7fb11ed852fb2d0ca6794762b42406c73154f6b",
      "date": "2011-02-03T06:19:05Z"
    },
    {
      "dev_id": "michaeldv",
      "repo": "michaeldv/awesome_print",
      "type": "commit",
      "id": "2562c2b787c1f3253c85661d870cd8e1dedaa765",
      "date": "2011-01-28T03:51:17Z"
    },
    {
      "dev_id": "michaeldv",
      "repo": "michaeldv/awesome_print",
      "type": "commit",
      "id": "b2ce17dae6557fd739da0f569fa4731d48d4f45e",
      "date": "2011-01-28T03:14:03Z"
    },
    {
      "dev_id": "michaeldv",
      "repo": "michaeldv/awesome_print",
      "type": "commit",
      "id": "73b83af69eb73ffae519decabdc324d199a1f7c1",
      "date": "2010-11-13T17:59:29Z"
    },
    {
      "dev_id": "michaeldv",
      "repo": "michaeldv/awesome_print",
      "type": "commit",
      "id": "dff3cfea9710eab5ab9fdcb56281b7ac4e67f3b1",
      "date": "2010-11-13T17:49:24Z"
    },
    {
      "dev_id": "michaeldv",
      "repo": "michaeldv/awesome_print",
      "type": "commit",
      "id": "49c50598139fcefb71b70921ca4da9ee6e046aaa",
      "date": "2010-11-13T17:42:50Z"
    },
    {
      "dev_id": "michaeldv",
      "repo": "michaeldv/awesome_print",
      "type": "commit",
      "id": "934d2945925b30e9c8ee6b6b423fad5abc382b6d",
      "date": "2010-11-13T17:24:26Z"
    },
    {
      "dev_id": "michaeldv",
      "repo": "michaeldv/awesome_print",
      "type": "commit",
      "id": "fcbd18377af20f88db1b41b0c45861d3bc4ca6d4",
      "date": "2010-11-13T17:12:54Z"
    },
    {
      "dev_id": "michaeldv",
      "repo": "michaeldv/awesome_print",
      "type": "commit",
      "id": "bbefc738a5b72941db99be588fcbae4d6624ed66",
      "date": "2010-11-10T04:29:32Z"
    },
    {
      "dev_id": "michaeldv",
      "repo": "michaeldv/awesome_print",
      "type": "commit",
      "id": "3c14c1b74764a328b893cadfbc7d8ce3d2f0c2e8",
      "date": "2010-11-10T04:01:36Z"
    },
    {
      "dev_id": "michaeldv",
      "repo": "michaeldv/awesome_print",
      "type": "commit",
      "id": "b447e8e33def9891843a7d1beea607f6175e7664",
      "date": "2010-11-10T03:50:52Z"
    },
    {
      "dev_id": "michaeldv",
      "repo": "michaeldv/awesome_print",
      "type": "commit",
      "id": "d401b1471d26f9468734fc9645b0e26e97682e6d",
      "date": "2010-11-10T03:48:43Z"
    },
    {
      "dev_id": "michaeldv",
      "repo": "michaeldv/awesome_print",
      "type": "commit",
      "id": "777d16d91bcb3046b597072ff0a70c7b0a984645",
      "date": "2010-11-09T03:24:07Z"
    },
    {
      "dev_id": "michaeldv",
      "repo": "michaeldv/awesome_print",
      "type": "commit",
      "id": "e2039d9f06a1e2a50f50017b30bf0d0efedc7f7c",
      "date": "2010-11-06T23:01:38Z"
    },
    {
      "dev_id": "michaeldv",
      "repo": "michaeldv/awesome_print",
      "type": "commit",
      "id": "8432aa908661bb90618c5e1eec01ed83cfffb288",
      "date": "2010-11-06T22:40:20Z"
    },
    {
      "dev_id": "michaeldv",
      "repo": "michaeldv/awesome_print",
      "type": "commit",
      "id": "bddee7918ec07cbaaa0dbcd76f2d474df61cbb5d",
      "date": "2010-11-06T22:38:53Z"
    },
    {
      "dev_id": "michaeldv",
      "repo": "michaeldv/awesome_print",
      "type": "commit",
      "id": "c38b70cad45af428223270c58bef4a0b4e9af82c",
      "date": "2010-11-06T19:45:27Z"
    },
    {
      "dev_id": "michaeldv",
      "repo": "michaeldv/awesome_print",
      "type": "commit",
      "id": "57b215ff107ef81292376b67c7e55aa7114ba955",
      "date": "2010-11-06T02:45:24Z"
    },
    {
      "dev_id": "michaeldv",
      "repo": "michaeldv/awesome_print",
      "type": "commit",
      "id": "8f94cef98faee3e823f76d7bcf34c6d181d114c9",
      "date": "2010-11-06T01:31:54Z"
    },
    {
      "dev_id": "michaeldv",
      "repo": "michaeldv/awesome_print",
      "type": "commit",
      "id": "a0dab8cd57c4afb5e7ce2a942996fa235387d425",
      "date": "2010-11-01T05:34:50Z"
    },
    {
      "dev_id": "michaeldv",
      "repo": "michaeldv/awesome_print",
      "type": "commit",
      "id": "3ab0cbabc1aa98202f054bd8dd9a43ce7889b0be",
      "date": "2010-11-01T02:21:26Z"
    },
    {
      "dev_id": "michaeldv",
      "repo": "michaeldv/awesome_print",
      "type": "commit",
      "id": "816b5a6513bd8e9d2162adce454df39a09e38d82",
      "date": "2010-10-31T23:10:08Z"
    },
    {
      "dev_id": "michaeldv",
      "repo": "michaeldv/awesome_print",
      "type": "commit",
      "id": "5f78c06a05c427c1c38f15cc0d6dc1a0bdf77638",
      "date": "2010-10-31T22:02:12Z"
    },
    {
      "dev_id": "michaeldv",
      "repo": "michaeldv/awesome_print",
      "type": "commit",
      "id": "14e4fd5e7dfa3e2f9934cec55191d31f874338dd",
      "date": "2010-10-30T20:50:48Z"
    },
    {
      "dev_id": "michaeldv",
      "repo": "michaeldv/awesome_print",
      "type": "commit",
      "id": "4dde5baab483831e75a3d32473f2359748ba12bd",
      "date": "2010-10-13T06:03:37Z"
    },
    {
      "dev_id": "michaeldv",
      "repo": "michaeldv/awesome_print",
      "type": "commit",
      "id": "75700ea33093394411a5af5b89c069301c48fd99",
      "date": "2010-10-13T05:52:53Z"
    },
    {
      "dev_id": "michaeldv",
      "repo": "michaeldv/awesome_print",
      "type": "commit",
      "id": "620c83dd842d9cda5ce540995f53b3d6fa612e15",
      "date": "2010-06-04T05:04:12Z"
    },
    {
      "dev_id": "michaeldv",
      "repo": "michaeldv/awesome_print",
      "type": "commit",
      "id": "d3c7d07f9893b6c9abfe9cc6276ebb1074253810",
      "date": "2010-06-04T02:53:47Z"
    },
    {
      "dev_id": "michaeldv",
      "repo": "michaeldv/awesome_print",
      "type": "commit",
      "id": "fe58321517ef6a491d0f9ee1cf83dc884f5091ea",
      "date": "2010-06-04T02:39:09Z"
    },
    {
      "dev_id": "michaeldv",
      "repo": "michaeldv/awesome_print",
      "type": "commit",
      "id": "bc0ca80936962467d2062f8c6d1ac4a53c3cf5bd",
      "date": "2010-05-22T16:48:49Z"
    },
    {
      "dev_id": "michaeldv",
      "repo": "michaeldv/awesome_print",
      "type": "commit",
      "id": "5ee3eaeb578cfc827ac30f51d6a872a4e41a7218",
      "date": "2010-05-22T05:53:03Z"
    },
    {
      "dev_id": "michaeldv",
      "repo": "michaeldv/awesome_print",
      "type": "commit",
      "id": "2f8e31ebe35d8a3eab8903eae1bbd7761dc5fa51",
      "date": "2010-05-13T05:09:23Z"
    },
    {
      "dev_id": "michaeldv",
      "repo": "michaeldv/awesome_print",
      "type": "commit",
      "id": "c9781fc974dbdb82bbf6edbec073b9723afa7377",
      "date": "2010-05-13T05:03:33Z"
    },
    {
      "dev_id": "michaeldv",
      "repo": "michaeldv/awesome_print",
      "type": "commit",
      "id": "ba89f3ddaf35f6a145d56a7b3f56f8bca373300b",
      "date": "2010-05-06T05:23:18Z"
    },
    {
      "dev_id": "michaeldv",
      "repo": "michaeldv/awesome_print",
      "type": "commit",
      "id": "d2017f66c5195f6c782c1786de21799b1dfab10e",
      "date": "2010-05-06T04:30:00Z"
    },
    {
      "dev_id": "michaeldv",
      "repo": "michaeldv/awesome_print",
      "type": "commit",
      "id": "40494e62dffe5b4e1ee7fe007ccf9ab662f9f384",
      "date": "2010-04-25T23:23:54Z"
    },
    {
      "dev_id": "michaeldv",
      "repo": "michaeldv/awesome_print",
      "type": "commit",
      "id": "bf2eaf30e31582b8c21ea2eee593ae0ec3902083",
      "date": "2010-04-09T03:40:38Z"
    },
    {
      "dev_id": "michaeldv",
      "repo": "michaeldv/awesome_print",
      "type": "commit",
      "id": "993bc0fc9a2fb09393567ab5a85e31bc94b9c76e",
      "date": "2010-04-09T03:31:53Z"
    },
    {
      "dev_id": "michaeldv",
      "repo": "michaeldv/awesome_print",
      "type": "commit",
      "id": "0b472a7da33f4f2858c2b3f41c2994cfa4aa3e87",
      "date": "2010-04-09T03:14:55Z"
    },
    {
      "dev_id": "michaeldv",
      "repo": "michaeldv/awesome_print",
      "type": "commit",
      "id": "d84c376bdc68f2cb0b43bbe66dfb19ac96b921e9",
      "date": "2010-04-09T03:14:47Z"
    },
    {
      "dev_id": "michaeldv",
      "repo": "michaeldv/awesome_print",
      "type": "commit",
      "id": "bf3c9915b649f1d2823226607580abbc96490fe9",
      "date": "2010-04-09T02:57:58Z"
    },
    {
      "dev_id": "michaeldv",
      "repo": "michaeldv/awesome_print",
      "type": "commit",
      "id": "936d73e6e94a7bbcab4b3c9a4021ec3f789ca3bf",
      "date": "2010-04-08T04:31:21Z"
    },
    {
      "dev_id": "michaeldv",
      "repo": "michaeldv/awesome_print",
      "type": "commit",
      "id": "7fe38425a54dd51b096381af87e1610002f0eb16",
      "date": "2010-04-07T04:30:12Z"
    },
    {
      "dev_id": "michaeldv",
      "repo": "michaeldv/awesome_print",
      "type": "commit",
      "id": "8044d58a518d1ba13eaf87e8385728bc649b6eda",
      "date": "2010-04-06T04:21:57Z"
    },
    {
      "dev_id": "michaeldv",
      "repo": "michaeldv/awesome_print",
      "type": "commit",
      "id": "ac770dad732b6b9780d27aa93f879f20e1ae10d3",
      "date": "2010-04-06T03:50:56Z"
    },
    {
      "dev_id": "michaeldv",
      "repo": "michaeldv/awesome_print",
      "type": "commit",
      "id": "0fddf1e5b5bcd3fb26dddf42f8826ad1485cbe3d",
      "date": "2010-04-06T03:24:46Z"
    },
    {
      "dev_id": "michaeldv",
      "repo": "michaeldv/awesome_print",
      "type": "commit",
      "id": "40df70cea535415dbd481d9a93c5234c645107d5",
      "date": "2010-04-06T03:05:30Z"
    },
    {
      "dev_id": "michaeldv",
      "repo": "michaeldv/awesome_print",
      "type": "commit",
      "id": "6e4117d495369717730ae8a79ed5a059b06ed69b",
      "date": "2010-04-06T03:02:07Z"
    },
    {
      "dev_id": "michaeldv",
      "repo": "michaeldv/awesome_print",
      "type": "commit",
      "id": "eb1cf1d0fed5f9f9be22ea082ed78079c00bbd65",
      "date": "2010-04-05T03:18:19Z"
    },
    {
      "dev_id": "michaeldv",
      "repo": "michaeldv/awesome_print",
      "type": "commit",
      "id": "29d041778e7b510ff1057c8164f824d80d455b4f",
      "date": "2010-04-05T03:10:16Z"
    },
    {
      "dev_id": "michaeldv",
      "repo": "michaeldv/awesome_print",
      "type": "commit",
      "id": "c6acd66ee89f856aa1f49cc38bff76538bf6fbca",
      "date": "2010-04-04T04:42:31Z"
    },
    {
      "dev_id": "michaeldv",
      "repo": "michaeldv/awesome_print",
      "type": "commit",
      "id": "7e35764f3d3a732d3c5fadff7dd646db74e60348",
      "date": "2010-04-04T04:37:13Z"
    },
    {
      "dev_id": "michaeldv",
      "repo": "michaeldv/awesome_print",
      "type": "commit",
      "id": "8a34aa45818998cbf92b394eb3c385dac2b01ac9",
      "date": "2010-04-04T04:28:49Z"
    },
    {
      "dev_id": "michaeldv",
      "repo": "michaeldv/awesome_print",
      "type": "commit",
      "id": "3fcea7fb057409add819b14422fa9224433197ab",
      "date": "2010-04-03T06:51:23Z"
    },
    {
      "dev_id": "michaeldv",
      "repo": "michaeldv/awesome_print",
      "type": "commit",
      "id": "4ac2bfd653127257ac1a07a8bed3abf1163fe039",
      "date": "2010-04-03T04:43:46Z"
    },
    {
      "dev_id": "michaeldv",
      "repo": "michaeldv/awesome_print",
      "type": "commit",
      "id": "55cdefadf1e05752fa688a5fffd4f8dd5c30749d",
      "date": "2010-03-28T04:08:13Z"
    },
    {
      "dev_id": "michaeldv",
      "repo": "michaeldv/awesome_print",
      "type": "commit",
      "id": "25786aacd8d3b4da3732bc60420515345c2b933e",
      "date": "2010-03-25T04:31:59Z"
    },
    {
      "dev_id": "michaeldv",
      "repo": "michaeldv/awesome_print",
      "type": "com",
      "id": 178728,
      "date": "2010-04-06T03:03:46Z"
    },
    {
      "dev_id": "michaeldv",
      "repo": "michaeldv/awesome_print",
      "type": "com",
      "id": 231205,
      "date": "2010-05-06T06:12:59Z"
    },
    {
      "dev_id": "michaeldv",
      "repo": "michaeldv/awesome_print",
      "type": "com",
      "id": 231206,
      "date": "2010-05-06T06:14:04Z"
    },
    {
      "dev_id": "michaeldv",
      "repo": "michaeldv/awesome_print",
      "type": "com",
      "id": 283132,
      "date": "2010-06-21T19:25:51Z"
    },
    {
      "dev_id": "michaeldv",
      "repo": "michaeldv/awesome_print",
      "type": "com",
      "id": 400340,
      "date": "2010-09-10T23:48:44Z"
    },
    {
      "dev_id": "michaeldv",
      "repo": "michaeldv/awesome_print",
      "type": "com",
      "id": 462554,
      "date": "2010-10-12T03:13:34Z"
    },
    {
      "dev_id": "michaeldv",
      "repo": "michaeldv/awesome_print",
      "type": "com",
      "id": 462557,
      "date": "2010-10-12T03:14:31Z"
    },
    {
      "dev_id": "michaeldv",
      "repo": "michaeldv/awesome_print",
      "type": "com",
      "id": 462574,
      "date": "2010-10-12T03:31:17Z"
    },
    {
      "dev_id": "michaeldv",
      "repo": "michaeldv/awesome_print",
      "type": "com",
      "id": 462667,
      "date": "2010-10-12T05:02:19Z"
    },
    {
      "dev_id": "michaeldv",
      "repo": "michaeldv/awesome_print",
      "type": "com",
      "id": 465329,
      "date": "2010-10-13T06:12:11Z"
    },
    {
      "dev_id": "michaeldv",
      "repo": "michaeldv/awesome_print",
      "type": "com",
      "id": 465333,
      "date": "2010-10-13T06:16:38Z"
    },
    {
      "dev_id": "michaeldv",
      "repo": "michaeldv/awesome_print",
      "type": "com",
      "id": 532268,
      "date": "2010-11-10T17:35:16Z"
    },
    {
      "dev_id": "michaeldv",
      "repo": "michaeldv/awesome_print",
      "type": "com",
      "id": 532285,
      "date": "2010-11-10T17:42:05Z"
    },
    {
      "dev_id": "michaeldv",
      "repo": "michaeldv/awesome_print",
      "type": "com",
      "id": 532331,
      "date": "2010-11-10T17:58:07Z"
    },
    {
      "dev_id": "michaeldv",
      "repo": "michaeldv/awesome_print",
      "type": "com",
      "id": 532504,
      "date": "2010-11-10T19:02:58Z"
    },
    {
      "dev_id": "michaeldv",
      "repo": "michaeldv/awesome_print",
      "type": "com",
      "id": 532515,
      "date": "2010-11-10T19:06:37Z"
    },
    {
      "dev_id": "michaeldv",
      "repo": "michaeldv/awesome_print",
      "type": "com",
      "id": 533844,
      "date": "2010-11-11T07:45:19Z"
    },
    {
      "dev_id": "michaeldv",
      "repo": "michaeldv/awesome_print",
      "type": "com",
      "id": 539074,
      "date": "2010-11-13T18:05:50Z"
    },
    {
      "dev_id": "michaeldv",
      "repo": "michaeldv/awesome_print",
      "type": "com",
      "id": 539077,
      "date": "2010-11-13T18:06:36Z"
    },
    {
      "dev_id": "michaeldv",
      "repo": "michaeldv/awesome_print",
      "type": "com",
      "id": 539079,
      "date": "2010-11-13T18:07:28Z"
    },
    {
      "dev_id": "michaeldv",
      "repo": "michaeldv/awesome_print",
      "type": "com",
      "id": 539084,
      "date": "2010-11-13T18:09:41Z"
    },
    {
      "dev_id": "michaeldv",
      "repo": "michaeldv/awesome_print",
      "type": "com",
      "id": 539087,
      "date": "2010-11-13T18:11:14Z"
    },
    {
      "dev_id": "michaeldv",
      "repo": "michaeldv/awesome_print",
      "type": "com",
      "id": 546944,
      "date": "2010-11-17T02:49:38Z"
    },
    {
      "dev_id": "michaeldv",
      "repo": "michaeldv/awesome_print",
      "type": "com",
      "id": 546981,
      "date": "2010-11-17T03:31:06Z"
    },
    {
      "dev_id": "michaeldv",
      "repo": "michaeldv/awesome_print",
      "type": "com",
      "id": 549709,
      "date": "2010-11-18T02:48:58Z"
    },
    {
      "dev_id": "michaeldv",
      "repo": "michaeldv/awesome_print",
      "type": "com",
      "id": 554509,
      "date": "2010-11-19T20:50:12Z"
    },
    {
      "dev_id": "michaeldv",
      "repo": "michaeldv/awesome_print",
      "type": "com",
      "id": 596228,
      "date": "2010-12-08T05:48:47Z"
    },
    {
      "dev_id": "michaeldv",
      "repo": "michaeldv/awesome_print",
      "type": "com",
      "id": 596249,
      "date": "2010-12-08T06:06:05Z"
    },
    {
      "dev_id": "michaeldv",
      "repo": "michaeldv/awesome_print",
      "type": "com",
      "id": 596287,
      "date": "2010-12-08T06:53:58Z"
    },
    {
      "dev_id": "michaeldv",
      "repo": "michaeldv/awesome_print",
      "type": "com",
      "id": 596288,
      "date": "2010-12-08T06:56:56Z"
    },
    {
      "dev_id": "michaeldv",
      "repo": "michaeldv/awesome_print",
      "type": "com",
      "id": 596299,
      "date": "2010-12-08T07:11:51Z"
    },
    {
      "dev_id": "michaeldv",
      "repo": "michaeldv/awesome_print",
      "type": "com",
      "id": 626287,
      "date": "2010-12-21T01:44:10Z"
    },
    {
      "dev_id": "michaeldv",
      "repo": "michaeldv/awesome_print",
      "type": "com",
      "id": 637140,
      "date": "2010-12-27T18:54:09Z"
    },
    {
      "dev_id": "michaeldv",
      "repo": "michaeldv/awesome_print",
      "type": "com",
      "id": 713963,
      "date": "2011-01-27T06:22:58Z"
    },
    {
      "dev_id": "michaeldv",
      "repo": "michaeldv/awesome_print",
      "type": "com",
      "id": 713967,
      "date": "2011-01-27T06:25:49Z"
    },
    {
      "dev_id": "michaeldv",
      "repo": "michaeldv/awesome_print",
      "type": "com",
      "id": 713977,
      "date": "2011-01-27T06:30:00Z"
    },
    {
      "dev_id": "michaeldv",
      "repo": "michaeldv/awesome_print",
      "type": "com",
      "id": 716989,
      "date": "2011-01-28T03:07:38Z"
    },
    {
      "dev_id": "michaeldv",
      "repo": "michaeldv/awesome_print",
      "type": "com",
      "id": 717063,
      "date": "2011-01-28T03:54:07Z"
    },
    {
      "dev_id": "michaeldv",
      "repo": "michaeldv/awesome_print",
      "type": "com",
      "id": 717065,
      "date": "2011-01-28T03:54:36Z"
    },
    {
      "dev_id": "michaeldv",
      "repo": "michaeldv/awesome_print",
      "type": "com",
      "id": 717075,
      "date": "2011-01-28T03:59:06Z"
    },
    {
      "dev_id": "michaeldv",
      "repo": "michaeldv/awesome_print",
      "type": "com",
      "id": 733739,
      "date": "2011-02-02T21:41:44Z"
    },
    {
      "dev_id": "michaeldv",
      "repo": "michaeldv/awesome_print",
      "type": "com",
      "id": 734995,
      "date": "2011-02-03T07:28:59Z"
    },
    {
      "dev_id": "michaeldv",
      "repo": "michaeldv/awesome_print",
      "type": "com",
      "id": 828208,
      "date": "2011-03-02T22:55:05Z"
    },
    {
      "dev_id": "michaeldv",
      "repo": "michaeldv/awesome_print",
      "type": "com",
      "id": 845377,
      "date": "2011-03-08T00:36:04Z"
    },
    {
      "dev_id": "michaeldv",
      "repo": "michaeldv/awesome_print",
      "type": "com",
      "id": 845484,
      "date": "2011-03-08T01:07:56Z"
    },
    {
      "dev_id": "michaeldv",
      "repo": "michaeldv/awesome_print",
      "type": "com",
      "id": 848560,
      "date": "2011-03-08T19:30:57Z"
    },
    {
      "dev_id": "michaeldv",
      "repo": "michaeldv/awesome_print",
      "type": "com",
      "id": 858140,
      "date": "2011-03-10T21:55:28Z"
    },
    {
      "dev_id": "michaeldv",
      "repo": "michaeldv/awesome_print",
      "type": "com",
      "id": 859454,
      "date": "2011-03-11T04:59:11Z"
    },
    {
      "dev_id": "michaeldv",
      "repo": "michaeldv/awesome_print",
      "type": "com",
      "id": 1089458,
      "date": "2011-05-02T17:48:50Z"
    },
    {
      "dev_id": "michaeldv",
      "repo": "michaeldv/awesome_print",
      "type": "com",
      "id": 1090517,
      "date": "2011-05-02T20:44:42Z"
    },
    {
      "dev_id": "michaeldv",
      "repo": "michaeldv/awesome_print",
      "type": "com",
      "id": 1103357,
      "date": "2011-05-05T02:12:43Z"
    },
    {
      "dev_id": "michaeldv",
      "repo": "michaeldv/awesome_print",
      "type": "com",
      "id": 1103377,
      "date": "2011-05-05T02:21:05Z"
    },
    {
      "dev_id": "michaeldv",
      "repo": "michaeldv/awesome_print",
      "type": "com",
      "id": 1107168,
      "date": "2011-05-05T17:57:27Z"
    },
    {
      "dev_id": "michaeldv",
      "repo": "michaeldv/awesome_print",
      "type": "com",
      "id": 1108079,
      "date": "2011-05-05T20:40:42Z"
    },
    {
      "dev_id": "michaeldv",
      "repo": "michaeldv/awesome_print",
      "type": "com",
      "id": 1108140,
      "date": "2011-05-05T20:52:07Z"
    },
    {
      "dev_id": "michaeldv",
      "repo": "michaeldv/awesome_print",
      "type": "com",
      "id": 1108190,
      "date": "2011-05-05T20:59:41Z"
    },
    {
      "dev_id": "michaeldv",
      "repo": "michaeldv/awesome_print",
      "type": "com",
      "id": 1108661,
      "date": "2011-05-05T22:41:42Z"
    },
    {
      "dev_id": "michaeldv",
      "repo": "michaeldv/awesome_print",
      "type": "com",
      "id": 1112500,
      "date": "2011-05-06T17:29:44Z"
    },
    {
      "dev_id": "michaeldv",
      "repo": "michaeldv/awesome_print",
      "type": "com",
      "id": 1112556,
      "date": "2011-05-06T17:40:47Z"
    },
    {
      "dev_id": "michaeldv",
      "repo": "michaeldv/awesome_print",
      "type": "com",
      "id": 1113738,
      "date": "2011-05-06T21:34:56Z"
    },
    {
      "dev_id": "michaeldv",
      "repo": "michaeldv/awesome_print",
      "type": "com",
      "id": 1113910,
      "date": "2011-05-06T22:09:29Z"
    },
    {
      "dev_id": "michaeldv",
      "repo": "michaeldv/awesome_print",
      "type": "com",
      "id": 1116163,
      "date": "2011-05-07T18:57:16Z"
    },
    {
      "dev_id": "michaeldv",
      "repo": "michaeldv/awesome_print",
      "type": "com",
      "id": 1116182,
      "date": "2011-05-07T19:01:15Z"
    },
    {
      "dev_id": "michaeldv",
      "repo": "michaeldv/awesome_print",
      "type": "com",
      "id": 1154884,
      "date": "2011-05-13T17:12:15Z"
    },
    {
      "dev_id": "michaeldv",
      "repo": "michaeldv/awesome_print",
      "type": "com",
      "id": 1171300,
      "date": "2011-05-16T04:39:56Z"
    },
    {
      "dev_id": "michaeldv",
      "repo": "michaeldv/awesome_print",
      "type": "com",
      "id": 1171312,
      "date": "2011-05-16T04:40:56Z"
    },
    {
      "dev_id": "michaeldv",
      "repo": "michaeldv/awesome_print",
      "type": "com",
      "id": 1171321,
      "date": "2011-05-16T04:41:26Z"
    },
    {
      "dev_id": "michaeldv",
      "repo": "michaeldv/awesome_print",
      "type": "com",
      "id": 1171337,
      "date": "2011-05-16T04:42:34Z"
    },
    {
      "dev_id": "michaeldv",
      "repo": "michaeldv/awesome_print",
      "type": "com",
      "id": 1171353,
      "date": "2011-05-16T04:43:25Z"
    },
    {
      "dev_id": "michaeldv",
      "repo": "michaeldv/awesome_print",
      "type": "com",
      "id": 1171404,
      "date": "2011-05-16T04:45:51Z"
    },
    {
      "dev_id": "michaeldv",
      "repo": "michaeldv/awesome_print",
      "type": "com",
      "id": 1171428,
      "date": "2011-05-16T04:47:35Z"
    },
    {
      "dev_id": "michaeldv",
      "repo": "michaeldv/awesome_print",
      "type": "com",
      "id": 1268922,
      "date": "2011-05-31T18:06:55Z"
    },
    {
      "dev_id": "michaeldv",
      "repo": "michaeldv/awesome_print",
      "type": "com",
      "id": 1269116,
      "date": "2011-05-31T18:35:14Z"
    },
    {
      "dev_id": "michaeldv",
      "repo": "michaeldv/awesome_print",
      "type": "com",
      "id": 1279192,
      "date": "2011-06-02T05:56:19Z"
    },
    {
      "dev_id": "michaeldv",
      "repo": "michaeldv/awesome_print",
      "type": "com",
      "id": 1279208,
      "date": "2011-06-02T06:01:33Z"
    },
    {
      "dev_id": "michaeldv",
      "repo": "michaeldv/awesome_print",
      "type": "com",
      "id": 1777491,
      "date": "2011-08-10T22:40:16Z"
    },
    {
      "dev_id": "michaeldv",
      "repo": "michaeldv/awesome_print",
      "type": "com",
      "id": 1777621,
      "date": "2011-08-10T23:01:19Z"
    },
    {
      "dev_id": "michaeldv",
      "repo": "michaeldv/awesome_print",
      "type": "com",
      "id": 2436336,
      "date": "2011-10-17T23:50:52Z"
    },
    {
      "dev_id": "michaeldv",
      "repo": "michaeldv/awesome_print",
      "type": "com",
      "id": 2562211,
      "date": "2011-10-28T22:56:47Z"
    },
    {
      "dev_id": "michaeldv",
      "repo": "michaeldv/awesome_print",
      "type": "com",
      "id": 2699956,
      "date": "2011-11-10T19:33:56Z"
    },
    {
      "dev_id": "michaeldv",
      "repo": "michaeldv/awesome_print",
      "type": "com",
      "id": 2699978,
      "date": "2011-11-10T19:36:07Z"
    },
    {
      "dev_id": "michaeldv",
      "repo": "michaeldv/awesome_print",
      "type": "com",
      "id": 2858444,
      "date": "2011-11-24T05:22:15Z"
    },
    {
      "dev_id": "michaeldv",
      "repo": "michaeldv/awesome_print",
      "type": "com",
      "id": 2983766,
      "date": "2011-12-01T23:22:14Z"
    },
    {
      "dev_id": "michaeldv",
      "repo": "michaeldv/awesome_print",
      "type": "com",
      "id": 2983786,
      "date": "2011-12-01T23:24:15Z"
    },
    {
      "dev_id": "michaeldv",
      "repo": "michaeldv/awesome_print",
      "type": "com",
      "id": 2983799,
      "date": "2011-12-01T23:25:30Z"
    },
    {
      "dev_id": "michaeldv",
      "repo": "michaeldv/awesome_print",
      "type": "com",
      "id": 2983813,
      "date": "2011-12-01T23:27:01Z"
    },
    {
      "dev_id": "michaeldv",
      "repo": "michaeldv/awesome_print",
      "type": "com",
      "id": 2983819,
      "date": "2011-12-01T23:27:44Z"
    },
    {
      "dev_id": "michaeldv",
      "repo": "michaeldv/awesome_print",
      "type": "com",
      "id": 2983830,
      "date": "2011-12-01T23:28:49Z"
    },
    {
      "dev_id": "michaeldv",
      "repo": "michaeldv/awesome_print",
      "type": "com",
      "id": 2983835,
      "date": "2011-12-01T23:29:37Z"
    },
    {
      "dev_id": "michaeldv",
      "repo": "michaeldv/awesome_print",
      "type": "com",
      "id": 2983844,
      "date": "2011-12-01T23:30:07Z"
    },
    {
      "dev_id": "michaeldv",
      "repo": "michaeldv/awesome_print",
      "type": "com",
      "id": 2983865,
      "date": "2011-12-01T23:31:28Z"
    },
    {
      "dev_id": "michaeldv",
      "repo": "michaeldv/awesome_print",
      "type": "com",
      "id": 2983871,
      "date": "2011-12-01T23:31:55Z"
    },
    {
      "dev_id": "michaeldv",
      "repo": "michaeldv/awesome_print",
      "type": "com",
      "id": 2983876,
      "date": "2011-12-01T23:32:18Z"
    },
    {
      "dev_id": "michaeldv",
      "repo": "michaeldv/awesome_print",
      "type": "com",
      "id": 2983883,
      "date": "2011-12-01T23:32:43Z"
    },
    {
      "dev_id": "michaeldv",
      "repo": "michaeldv/awesome_print",
      "type": "com",
      "id": 2983889,
      "date": "2011-12-01T23:33:06Z"
    },
    {
      "dev_id": "michaeldv",
      "repo": "michaeldv/awesome_print",
      "type": "com",
      "id": 2983896,
      "date": "2011-12-01T23:33:51Z"
    },
    {
      "dev_id": "michaeldv",
      "repo": "michaeldv/awesome_print",
      "type": "com",
      "id": 2983912,
      "date": "2011-12-01T23:34:51Z"
    },
    {
      "dev_id": "michaeldv",
      "repo": "michaeldv/awesome_print",
      "type": "com",
      "id": 2994855,
      "date": "2011-12-02T19:51:04Z"
    },
    {
      "dev_id": "michaeldv",
      "repo": "michaeldv/awesome_print",
      "type": "com",
      "id": 2994933,
      "date": "2011-12-02T19:57:51Z"
    },
    {
      "dev_id": "michaeldv",
      "repo": "michaeldv/awesome_print",
      "type": "com",
      "id": 2997577,
      "date": "2011-12-02T23:49:23Z"
    },
    {
      "dev_id": "michaeldv",
      "repo": "michaeldv/awesome_print",
      "type": "com",
      "id": 2997637,
      "date": "2011-12-02T23:58:30Z"
    },
    {
      "dev_id": "michaeldv",
      "repo": "michaeldv/awesome_print",
      "type": "com",
      "id": 2998136,
      "date": "2011-12-03T01:04:15Z"
    },
    {
      "dev_id": "michaeldv",
      "repo": "michaeldv/awesome_print",
      "type": "com",
      "id": 2998152,
      "date": "2011-12-03T01:08:05Z"
    },
    {
      "dev_id": "michaeldv",
      "repo": "michaeldv/awesome_print",
      "type": "com",
      "id": 2998727,
      "date": "2011-12-03T03:02:34Z"
    },
    {
      "dev_id": "michaeldv",
      "repo": "michaeldv/awesome_print",
      "type": "com",
      "id": 3074224,
      "date": "2011-12-09T01:34:11Z"
    },
    {
      "dev_id": "michaeldv",
      "repo": "michaeldv/awesome_print",
      "type": "com",
      "id": 3074466,
      "date": "2011-12-09T02:00:46Z"
    },
    {
      "dev_id": "michaeldv",
      "repo": "michaeldv/awesome_print",
      "type": "com",
      "id": 3118021,
      "date": "2011-12-13T02:49:19Z"
    },
    {
      "dev_id": "michaeldv",
      "repo": "michaeldv/awesome_print",
      "type": "com",
      "id": 3133187,
      "date": "2011-12-14T00:11:25Z"
    },
    {
      "dev_id": "michaeldv",
      "repo": "michaeldv/awesome_print",
      "type": "com",
      "id": 3133241,
      "date": "2011-12-14T00:16:47Z"
    },
    {
      "dev_id": "michaeldv",
      "repo": "michaeldv/awesome_print",
      "type": "com",
      "id": 3133285,
      "date": "2011-12-14T00:19:52Z"
    },
    {
      "dev_id": "michaeldv",
      "repo": "michaeldv/awesome_print",
      "type": "com",
      "id": 3185462,
      "date": "2011-12-16T23:25:23Z"
    },
    {
      "dev_id": "michaeldv",
      "repo": "michaeldv/awesome_print",
      "type": "com",
      "id": 3185623,
      "date": "2011-12-16T23:28:14Z"
    },
    {
      "dev_id": "michaeldv",
      "repo": "michaeldv/awesome_print",
      "type": "com",
      "id": 3186344,
      "date": "2011-12-16T23:59:26Z"
    },
    {
      "dev_id": "michaeldv",
      "repo": "michaeldv/awesome_print",
      "type": "com",
      "id": 3188070,
      "date": "2011-12-17T06:23:55Z"
    },
    {
      "dev_id": "michaeldv",
      "repo": "michaeldv/awesome_print",
      "type": "com",
      "id": 3188081,
      "date": "2011-12-17T06:26:38Z"
    },
    {
      "dev_id": "michaeldv",
      "repo": "michaeldv/awesome_print",
      "type": "com",
      "id": 3193689,
      "date": "2011-12-18T08:15:01Z"
    },
    {
      "dev_id": "michaeldv",
      "repo": "michaeldv/awesome_print",
      "type": "com",
      "id": 3196642,
      "date": "2011-12-18T20:16:51Z"
    },
    {
      "dev_id": "michaeldv",
      "repo": "michaeldv/awesome_print",
      "type": "com",
      "id": 3197280,
      "date": "2011-12-18T22:11:35Z"
    },
    {
      "dev_id": "michaeldv",
      "repo": "michaeldv/awesome_print",
      "type": "com",
      "id": 3197844,
      "date": "2011-12-18T23:56:28Z"
    },
    {
      "dev_id": "michaeldv",
      "repo": "michaeldv/awesome_print",
      "type": "com",
      "id": 3207758,
      "date": "2011-12-19T19:03:39Z"
    },
    {
      "dev_id": "michaeldv",
      "repo": "michaeldv/awesome_print",
      "type": "com",
      "id": 3207820,
      "date": "2011-12-19T19:07:43Z"
    },
    {
      "dev_id": "michaeldv",
      "repo": "michaeldv/awesome_print",
      "type": "com",
      "id": 3229504,
      "date": "2011-12-21T04:38:35Z"
    },
    {
      "dev_id": "michaeldv",
      "repo": "michaeldv/awesome_print",
      "type": "com",
      "id": 3229506,
      "date": "2011-12-21T04:38:56Z"
    },
    {
      "dev_id": "michaeldv",
      "repo": "michaeldv/awesome_print",
      "type": "com",
      "id": 3229510,
      "date": "2011-12-21T04:39:15Z"
    },
    {
      "dev_id": "michaeldv",
      "repo": "michaeldv/awesome_print",
      "type": "com",
      "id": 3229512,
      "date": "2011-12-21T04:39:32Z"
    },
    {
      "dev_id": "michaeldv",
      "repo": "michaeldv/awesome_print",
      "type": "com",
      "id": 3229565,
      "date": "2011-12-21T04:47:19Z"
    },
    {
      "dev_id": "michaeldv",
      "repo": "michaeldv/awesome_print",
      "type": "com",
      "id": 3242538,
      "date": "2011-12-22T01:59:32Z"
    },
    {
      "dev_id": "michaeldv",
      "repo": "michaeldv/awesome_print",
      "type": "com",
      "id": 3245896,
      "date": "2011-12-22T06:14:14Z"
    },
    {
      "dev_id": "michaeldv",
      "repo": "michaeldv/awesome_print",
      "type": "com",
      "id": 3245916,
      "date": "2011-12-22T06:17:24Z"
    },
    {
      "dev_id": "michaeldv",
      "repo": "michaeldv/awesome_print",
      "type": "com",
      "id": 3246111,
      "date": "2011-12-22T06:51:16Z"
    },
    {
      "dev_id": "michaeldv",
      "repo": "michaeldv/awesome_print",
      "type": "com",
      "id": 3246305,
      "date": "2011-12-22T07:26:50Z"
    },
    {
      "dev_id": "michaeldv",
      "repo": "michaeldv/awesome_print",
      "type": "com",
      "id": 4307240,
      "date": "2012-03-04T03:24:40Z"
    },
    {
      "dev_id": "michaeldv",
      "repo": "michaeldv/awesome_print",
      "type": "com",
      "id": 4425138,
      "date": "2012-03-09T21:36:02Z"
    },
    {
      "dev_id": "michaeldv",
      "repo": "michaeldv/awesome_print",
      "type": "com",
      "id": 5401945,
      "date": "2012-04-29T01:57:12Z"
    },
    {
      "dev_id": "michaeldv",
      "repo": "michaeldv/awesome_print",
      "type": "com",
      "id": 5630969,
      "date": "2012-05-10T17:14:49Z"
    },
    {
      "dev_id": "michaeldv",
      "repo": "michaeldv/awesome_print",
      "type": "com",
      "id": 8246175,
      "date": "2012-09-03T20:10:54Z"
    },
    {
      "dev_id": "michaeldv",
      "repo": "michaeldv/awesome_print",
      "type": "com",
      "id": 8247098,
      "date": "2012-09-03T21:09:08Z"
    },
    {
      "dev_id": "michaeldv",
      "repo": "michaeldv/awesome_print",
      "type": "com",
      "id": 8247116,
      "date": "2012-09-03T21:10:11Z"
    },
    {
      "dev_id": "michaeldv",
      "repo": "michaeldv/awesome_print",
      "type": "com",
      "id": 8249653,
      "date": "2012-09-04T00:28:38Z"
    },
    {
      "dev_id": "michaeldv",
      "repo": "michaeldv/awesome_print",
      "type": "com",
      "id": 8302076,
      "date": "2012-09-05T15:09:04Z"
    },
    {
      "dev_id": "michaeldv",
      "repo": "michaeldv/awesome_print",
      "type": "com",
      "id": 8397209,
      "date": "2012-09-08T19:54:37Z"
    },
    {
      "dev_id": "michaeldv",
      "repo": "michaeldv/awesome_print",
      "type": "com",
      "id": 8624662,
      "date": "2012-09-17T18:03:39Z"
    },
    {
      "dev_id": "michaeldv",
      "repo": "michaeldv/awesome_print",
      "type": "com",
      "id": 9690244,
      "date": "2012-10-23T04:21:49Z"
    },
    {
      "dev_id": "michaeldv",
      "repo": "michaeldv/awesome_print",
      "type": "com",
      "id": 10470649,
      "date": "2012-11-17T04:54:36Z"
    },
    {
      "dev_id": "michaeldv",
      "repo": "michaeldv/awesome_print",
      "type": "com",
      "id": 10673866,
      "date": "2012-11-24T04:32:58Z"
    },
    {
      "dev_id": "michaeldv",
      "repo": "michaeldv/awesome_print",
      "type": "com",
      "id": 11253427,
      "date": "2012-12-11T17:31:38Z"
    },
    {
      "dev_id": "michaeldv",
      "repo": "michaeldv/awesome_print",
      "type": "com",
      "id": 11324852,
      "date": "2012-12-13T07:21:51Z"
    },
    {
      "dev_id": "michaeldv",
      "repo": "michaeldv/awesome_print",
      "type": "com",
      "id": 24777869,
      "date": "2013-09-19T22:23:02Z"
    },
    {
      "dev_id": "michaeldv",
      "repo": "michaeldv/awesome_print",
      "type": "com",
      "id": 24779109,
      "date": "2013-09-19T22:47:07Z"
    },
    {
      "dev_id": "michaeldv",
      "repo": "michaeldv/awesome_print",
      "type": "com",
      "id": 24779351,
      "date": "2013-09-19T22:52:06Z"
    },
    {
      "dev_id": "michaeldv",
      "repo": "michaeldv/awesome_print",
      "type": "com",
      "id": 24779510,
      "date": "2013-09-19T22:55:28Z"
    },
    {
      "dev_id": "michaeldv",
      "repo": "michaeldv/awesome_print",
      "type": "com",
      "id": 24779566,
      "date": "2013-09-19T22:56:44Z"
    },
    {
      "dev_id": "michaeldv",
      "repo": "michaeldv/awesome_print",
      "type": "com",
      "id": 24779802,
      "date": "2013-09-19T23:01:58Z"
    },
    {
      "dev_id": "michaeldv",
      "repo": "michaeldv/awesome_print",
      "type": "com",
      "id": 24779888,
      "date": "2013-09-19T23:03:56Z"
    },
    {
      "dev_id": "michaeldv",
      "repo": "michaeldv/awesome_print",
      "type": "com",
      "id": 24779958,
      "date": "2013-09-19T23:05:33Z"
    },
    {
      "dev_id": "michaeldv",
      "repo": "michaeldv/awesome_print",
      "type": "com",
      "id": 24780008,
      "date": "2013-09-19T23:06:51Z"
    },
    {
      "dev_id": "michaeldv",
      "repo": "michaeldv/awesome_print",
      "type": "com",
      "id": 24780099,
      "date": "2013-09-19T23:09:35Z"
    },
    {
      "dev_id": "michaeldv",
      "repo": "michaeldv/awesome_print",
      "type": "com",
      "id": 24780283,
      "date": "2013-09-19T23:14:08Z"
    },
    {
      "dev_id": "michaeldv",
      "repo": "michaeldv/awesome_print",
      "type": "com",
      "id": 24780400,
      "date": "2013-09-19T23:16:44Z"
    },
    {
      "dev_id": "michaeldv",
      "repo": "michaeldv/awesome_print",
      "type": "com",
      "id": 24780683,
      "date": "2013-09-19T23:23:12Z"
    },
    {
      "dev_id": "michaeldv",
      "repo": "michaeldv/awesome_print",
      "type": "com",
      "id": 24780719,
      "date": "2013-09-19T23:24:03Z"
    },
    {
      "dev_id": "michaeldv",
      "repo": "michaeldv/awesome_print",
      "type": "com",
      "id": 24789883,
      "date": "2013-09-20T04:46:11Z"
    },
    {
      "dev_id": "michaeldv",
      "repo": "michaeldv/awesome_print",
      "type": "com",
      "id": 24869290,
      "date": "2013-09-21T19:42:12Z"
    },
    {
      "dev_id": "michaeldv",
      "repo": "michaeldv/awesome_print",
      "type": "com",
      "id": 24869309,
      "date": "2013-09-21T19:43:18Z"
    },
    {
      "dev_id": "michaeldv",
      "repo": "michaeldv/awesome_print",
      "type": "com",
      "id": 24869332,
      "date": "2013-09-21T19:44:17Z"
    },
    {
      "dev_id": "michaeldv",
      "repo": "michaeldv/awesome_print",
      "type": "com",
      "id": 24869344,
      "date": "2013-09-21T19:45:10Z"
    },
    {
      "dev_id": "michaeldv",
      "repo": "michaeldv/awesome_print",
      "type": "com",
      "id": 24869548,
      "date": "2013-09-21T19:58:54Z"
    },
    {
      "dev_id": "michaeldv",
      "repo": "michaeldv/awesome_print",
      "type": "com",
      "id": 25753604,
      "date": "2013-10-05T18:06:38Z"
    },
    {
      "dev_id": "michaeldv",
      "repo": "michaeldv/awesome_print",
      "type": "com",
      "id": 25753643,
      "date": "2013-10-05T18:08:19Z"
    },
    {
      "dev_id": "michaeldv",
      "repo": "michaeldv/awesome_print",
      "type": "com",
      "id": 25753721,
      "date": "2013-10-05T18:12:40Z"
    },
    {
      "dev_id": "michaeldv",
      "repo": "michaeldv/awesome_print",
      "type": "com",
      "id": 25755002,
      "date": "2013-10-05T19:13:08Z"
    },
    {
      "dev_id": "michaeldv",
      "repo": "michaeldv/awesome_print",
      "type": "com",
      "id": 27364926,
      "date": "2013-10-30T04:44:10Z"
    },
    {
      "dev_id": "michaeldv",
      "repo": "michaeldv/awesome_print",
      "type": "com",
      "id": 27801488,
      "date": "2013-11-05T18:59:12Z"
    },
    {
      "dev_id": "michaeldv",
      "repo": "michaeldv/awesome_print",
      "type": "com",
      "id": 27902868,
      "date": "2013-11-06T19:03:58Z"
    },
    {
      "dev_id": "michaeldv",
      "repo": "michaeldv/awesome_print",
      "type": "com",
      "id": 28359188,
      "date": "2013-11-13T03:02:56Z"
    },
    {
      "dev_id": "michaeldv",
      "repo": "michaeldv/awesome_print",
      "type": "com",
      "id": 30991613,
      "date": "2013-12-20T06:36:35Z"
    },
    {
      "dev_id": "michaeldv",
      "repo": "michaeldv/awesome_print",
      "type": "com",
      "id": 67369830,
      "date": "2014-12-17T18:38:44Z"
    },
    {
      "dev_id": "michaeldv",
      "repo": "michaeldv/awesome_print",
      "type": "com",
      "id": 69630392,
      "date": "2015-01-12T19:33:24Z"
    },
    {
      "dev_id": "michaeldv",
      "repo": "michaeldv/awesome_print",
      "type": "com",
      "id": 71141799,
      "date": "2015-01-23T03:17:33Z"
    },
    {
      "dev_id": "michaeldv",
      "repo": "michaeldv/awesome_print",
      "type": "com",
      "id": 83310582,
      "date": "2015-03-19T04:10:30Z"
    },
    {
      "dev_id": "michaeldv",
      "repo": "michaeldv/awesome_print",
      "type": "com",
      "id": 83710204,
      "date": "2015-03-19T18:39:13Z"
    },
    {
      "dev_id": "michaeldv",
      "repo": "michaeldv/awesome_print",
      "type": "com",
      "id": 84161306,
      "date": "2015-03-20T21:45:30Z"
    },
    {
      "dev_id": "michaeldv",
      "repo": "michaeldv/awesome_print",
      "type": "com",
      "id": 94314411,
      "date": "2015-04-19T21:08:26Z"
    },
    {
      "dev_id": "michaeldv",
      "repo": "michaeldv/awesome_print",
      "type": "com",
      "id": 94996558,
      "date": "2015-04-22T01:54:32Z"
    },
    {
      "dev_id": "michaeldv",
      "repo": "michaeldv/awesome_print",
      "type": "com",
      "id": 113692088,
      "date": "2015-06-20T01:26:24Z"
    },
    {
      "dev_id": "michaeldv",
      "repo": "michaeldv/awesome_print",
      "type": "com",
      "id": 113694945,
      "date": "2015-06-20T01:42:37Z"
    },
    {
      "dev_id": "michaeldv",
      "repo": "michaeldv/awesome_print",
      "type": "com",
      "id": 113695179,
      "date": "2015-06-20T01:49:17Z"
    },
    {
      "dev_id": "michaeldv",
      "repo": "michaeldv/awesome_print",
      "type": "com",
      "id": 116916853,
      "date": "2015-06-30T02:30:35Z"
    },
    {
      "dev_id": "michaeldv",
      "repo": "defunkt/fakefs",
      "type": "com",
      "id": 1108650,
      "date": "2011-05-05T22:39:09Z"
    },
    {
      "dev_id": "michaeldv",
      "repo": "michaeldv/awesome_print",
      "type": "pr",
      "id": 170,
      "date": "2014-12-18T05:07:13Z"
    }
  ]
}